{
    "error": null,
    "data": {
        "rows": [
            {
                "01 contract": 289,
                "02 contracts": 102,
                "03-05 contracts": 271,
                "06-10 contracts": 444,
                "11-20 contracts": 975,
                "21-50 contracts": 3555,
                "51-100 contracts": 6969,
                "Over 100 contracts": 6307,
                "days_category": "Over 100 days",
                "Sum": 18912
            },
            {
                "01 contract": 291,
                "02 contracts": 205,
                "03-05 contracts": 912,
                "06-10 contracts": 1567,
                "11-20 contracts": 4588,
                "21-50 contracts": 14700,
                "51-100 contracts": 19603,
                "Over 100 contracts": 4975,
                "days_category": "51-100 days",
                "Sum": 46841
            },
            {
                "01 contract": 1329,
                "02 contracts": 1183,
                "03-05 contracts": 3570,
                "06-10 contracts": 13887,
                "11-20 contracts": 61418,
                "21-50 contracts": 148355,
                "51-100 contracts": 38686,
                "Over 100 contracts": 2252,
                "days_category": "21-50 days",
                "Sum": 270680
            },
            {
                "01 contract": 2696,
                "02 contracts": 5455,
                "03-05 contracts": 13595,
                "06-10 contracts": 60710,
                "11-20 contracts": 208362,
                "21-50 contracts": 188297,
                "51-100 contracts": 10308,
                "Over 100 contracts": 156,
                "days_category": "11-20 days",
                "Sum": 489579
            },
            {
                "01 contract": 10080,
                "02 contracts": 11516,
                "03-05 contracts": 92656,
                "06-10 contracts": 180989,
                "11-20 contracts": 159851,
                "21-50 contracts": 49022,
                "51-100 contracts": 1429,
                "Over 100 contracts": 15,
                "days_category": "06-10 days",
                "Sum": 505558
            },
            {
                "01 contract": 64277,
                "02 contracts": 98046,
                "03-05 contracts": 207501,
                "06-10 contracts": 107503,
                "11-20 contracts": 37975,
                "21-50 contracts": 6609,
                "51-100 contracts": 151,
                "Over 100 contracts": 0,
                "days_category": "03-5 days",
                "Sum": 522062
            },
            {
                "01 contract": 161810,
                "02 contracts": 60557,
                "03-05 contracts": 46656,
                "06-10 contracts": 14887,
                "11-20 contracts": 3299,
                "21-50 contracts": 528,
                "51-100 contracts": 14,
                "Over 100 contracts": 0,
                "days_category": "02 days",
                "Sum": 287751
            },
            {
                "01 contract": 265893,
                "02 contracts": 35595,
                "03-05 contracts": 18045,
                "06-10 contracts": 5843,
                "11-20 contracts": 1126,
                "21-50 contracts": 251,
                "51-100 contracts": 9,
                "Over 100 contracts": 13,
                "days_category": "01 day",
                "Sum": 326775
            }
        ]
    },
    "status": "ok"
}